blade2blade/__init__.py
blade2blade/inference.py
blade2blade/training/__init__.py
blade2blade/training/trainer.py
blade2blade/training/utils.py
blade2blade/training/config/t5_good.yaml
blade2blade/training/config/trainer/default.yaml
blade2blade/training/custom_datasets/__init__.py
blade2blade/training/custom_datasets/prosocial.py
blade2blade/training/custom_datasets/utils.py
blade2blade-0.0.1.dist-info/WHEEL
blade2blade-0.0.1.dist-info/METADATA
blade2blade-0.0.1.dist-info/RECORD
