Metadata-Version: 2.1
Name: blade2blade
Version: 0.0.1
Summary: Adversarial Training and SFT for Bot Safety Models
Author-email: LAION-AI <contact@laion.ai>
Requires-Dist: datasets>=2.11.0
Requires-Dist: torch>=2.0.0
Requires-Dist: transformers>=4.27.4
Requires-Dist: hydra-core>=1.3.2
Requires-Dist: tokenizers>=0.13.2
Requires-Dist: wandb>=0.14.0 ; extra == "dev"
Provides-Extra: dev
